py3_kit/__datetime.py
py3_kit/__init__.py
py3_kit/__py3_execute__/__init__.py
py3_kit/__py3_logger__/__init__.py
py3_kit/__py3_web__/__init__.py
py3_kit/__string.py
py3_kit/_math.py
py3_kit/_pandas.py
py3_kit/_types.py
py3_kit/assets/file/linux/7zz
py3_kit/assets/file/linux/7zzs
py3_kit/assets/file/linux/rar
py3_kit/assets/file/linux/unrar
py3_kit/assets/file/mac/7zz
py3_kit/assets/file/mac/rar
py3_kit/assets/file/mac/unrar
py3_kit/assets/file/win/7zr.exe
py3_kit/assets/file/win/Rar.exe
py3_kit/assets/file/win/UnRAR.exe
py3_kit/assets.py
py3_kit/file.py
py3_kit/image.py
py3_kit/list.py
py3_kit/project.py
py3_kit/sql.py
py3_kit/validators.py
py3_kit-0.0.7.dist-info/METADATA
py3_kit-0.0.7.dist-info/WHEEL
py3_kit-0.0.7.dist-info/licenses/LICENSE
py3_kit-0.0.7.dist-info/RECORD
