Metadata-Version: 2.4
Name: py3-kit
Version: 0.0.7
Summary: python3 kit
License-File: LICENSE
Author: mathewgeola
Author-email: mathewgeola@gmail.com
Requires-Python: >=3.12,<3.15
Classifier: Programming Language :: Python :: 3
Classifier: Programming Language :: Python :: 3.12
Classifier: Programming Language :: Python :: 3.13
Classifier: Programming Language :: Python :: 3.14
Requires-Dist: arrow (>=1.4.0,<2.0.0)
Requires-Dist: opencv-python (>=4.12.0.88,<5.0.0.0)
Requires-Dist: openpyxl (>=3.1.5,<4.0.0)
Requires-Dist: oss2 (>=2.19.1,<3.0.0)
Requires-Dist: pandas (>=2.3.3,<3.0.0)
Requires-Dist: pillow (>=12.1.0,<13.0.0)
Requires-Dist: pillow-avif-plugin (>=1.5.2,<2.0.0)
Requires-Dist: py3-execute (>=0.0.5,<0.0.6)
Requires-Dist: py3-logger (>=0.0.7,<0.0.8)
Requires-Dist: py3-web (>=0.0.7,<0.0.8)
Requires-Dist: pyinstaller (>=6.17.0,<7.0.0)
Requires-Dist: sqlparse (>=0.5.5,<0.6.0)
